LICENSE.txt
MANIFEST.in
setup.py
rc_cbed/__init__.py
rc_cbed/example.py
rc_cbed/model.py
rc_cbed/test_data.h5
rc_cbed.egg-info/PKG-INFO
rc_cbed.egg-info/SOURCES.txt
rc_cbed.egg-info/dependency_links.txt
rc_cbed.egg-info/requires.txt
rc_cbed.egg-info/top_level.txt
rc_cbed/model/fingerprint.pb
rc_cbed/model/keras_metadata.pb
rc_cbed/model/saved_model.pb
rc_cbed/model/variables/variables.data-00000-of-00001
rc_cbed/model/variables/variables.index