Metadata-Version: 2.1
Name: rc-cbed
Version: 1.0.10
Summary: rc_cbed network design to restore and center CBED images
Home-page: https://github.com/Ivanlh20/rc_cbed
Author: Ivan Lobato
Author-email: ivanlh20@gmail.com
License: GPLv3
Classifier: Development Status :: 5 - Production/Stable
Classifier: Intended Audience :: Science/Research
Classifier: License :: OSI Approved :: GNU General Public License v3 (GPLv3)
Classifier: Operating System :: POSIX :: Linux
Classifier: Programming Language :: Python :: 3.10
License-File: LICENSE.txt
